HISTORY.rst
LICENSE
MANIFEST.in
README.rst
apidoc.json
dev-requirements.txt
pylintrc
pytest.ini
requirements.txt
setup.cfg
setup.py
tox.ini
guessit_rest.egg-info/PKG-INFO
guessit_rest.egg-info/SOURCES.txt
guessit_rest.egg-info/dependency_links.txt
guessit_rest.egg-info/entry_points.txt
guessit_rest.egg-info/requires.txt
guessit_rest.egg-info/top_level.txt
guessit_rest.egg-info/zip-safe
guessitrest/__init__.py
guessitrest/__main__.py
guessitrest/__version__.py
guessitrest/app.py
guessitrest/bootstrap.py
guessitrest/uwsgi.ini
guessitrest/test/__init__.py
guessitrest/test/conftest.py
guessitrest/test/test_bootstrap.py
guessitrest/test/test_main.py