Metadata-Version: 2.1
Name: guessit-rest
Version: 2.1.2
Summary: GuessIt - REST WebService
Home-page: http://github.com/guessit-io/guessit-rest
Author: Rémi Alvergnat
Author-email: toilal.dev@gmail.com
License: LGPLv3
Keywords: python library release parser name filename movies series episodes animes
Platform: UNKNOWN
Classifier: Development Status :: 5 - Production/Stable
Classifier: License :: OSI Approved :: GNU Lesser General Public License v3 (LGPLv3)
Classifier: Operating System :: OS Independent
Classifier: Intended Audience :: Developers
Classifier: Programming Language :: Python :: 2
Classifier: Programming Language :: Python :: 2.7
Classifier: Programming Language :: Python :: 3
Classifier: Programming Language :: Python :: 3.4
Classifier: Programming Language :: Python :: 3.5
Classifier: Programming Language :: Python :: 3.6
Classifier: Programming Language :: Python :: 3.7
Classifier: Topic :: Multimedia
Classifier: Topic :: Software Development :: Libraries :: Python Modules
Provides-Extra: dev
Provides-Extra: test
